CheeseChase/__init__.py
CheeseChase/__main__.py
CheeseChase/controller/__init__.py
CheeseChase/controller/events_manager.py
CheeseChase/controller/game_controller.py
CheeseChase/controller/levels_manager.py
CheeseChase/controller/pauser.py
CheeseChase/model/__init__.py
CheeseChase/model/cats.py
CheeseChase/model/cheeses.py
CheeseChase/model/constants.py
CheeseChase/model/entity.py
CheeseChase/model/mazedata.py
CheeseChase/model/modes.py
CheeseChase/model/mouse.py
CheeseChase/model/nodes.py
CheeseChase/model/vector.py
CheeseChase/resources/PressStart2P-Regular.ttf
CheeseChase/resources/__init__.py
CheeseChase/resources/maze1.txt
CheeseChase/resources/maze1_rotation.txt
CheeseChase/resources/maze2.txt
CheeseChase/resources/maze2_rotation.txt
CheeseChase/resources/spritesheet2.png
CheeseChase/view/__init__.py
CheeseChase/view/animation.py
CheeseChase/view/game_view.py
CheeseChase/view/sprites.py
CheeseChase/view/text.py
cheesechase-1.8.4.dist-info/licenses/LICENSE
cheesechase-1.8.4.dist-info/METADATA
cheesechase-1.8.4.dist-info/WHEEL
cheesechase-1.8.4.dist-info/top_level.txt
cheesechase-1.8.4.dist-info/RECORD
