Metadata-Version: 2.4
Name: CheeseChase
Version: 1.8.4
Summary: Cheese-Chase is a modern remake of the classic arcade game Pac-Man, reimagined in the world of Tom & Jerry.
Home-page: https://github.com/aequitas-aod/my_project
Author: Francesca Folli, Gaia Bellachioma, Asia Zanotti
Author-email: francesca.folli2@studio.unibo.it, gaia.bellachioma@studio.unibo.it, asia.zanotti@studio.unibo.it
License: Apache 2.0 License
Project-URL: Bug Reports, https://github.com/aequitas-aod/my_project/issues
Project-URL: Source, https://github.com/aequitas-aod/my_project
Keywords: aeuitas,horizon2020,xai,bias
Platform: Independant
Classifier: Development Status :: 3 - Alpha
Classifier: Intended Audience :: Developers
Classifier: Topic :: Software Development :: Libraries
Classifier: Topic :: Scientific/Engineering :: Artificial Intelligence
Classifier: License :: OSI Approved :: Apache Software License
Classifier: Programming Language :: Python :: 3
Classifier: Programming Language :: Python :: 3 :: Only
Requires-Python: >=3.12.4
License-File: LICENSE
Requires-Dist: pygame>=2.5.0
Requires-Dist: numpy>=1.26.4
Dynamic: author
Dynamic: author-email
Dynamic: classifier
Dynamic: description
Dynamic: description-content-type
Dynamic: home-page
Dynamic: keywords
Dynamic: license
Dynamic: license-file
Dynamic: platform
Dynamic: project-url
Dynamic: requires-dist
Dynamic: requires-python
Dynamic: summary
